STRling/__init__.py
STRling/core/__init__.py
STRling/core/compiler.py
STRling/core/ir.py
STRling/core/nodes.py
STRling/core/parser.py
STRling/core/validator.py
STRling/emitters/__init__.py
STRling/emitters/pcre2.py
STRling/simply/__init__.py
STRling/simply/constructors.py
STRling/simply/lookarounds.py
STRling/simply/pattern.py
STRling/simply/sets.py
STRling/simply/static.py
strling-2.5.9.dist-info/METADATA
strling-2.5.9.dist-info/WHEEL
strling-2.5.9.dist-info/top_level.txt
strling-2.5.9.dist-info/RECORD
