Metadata-Version: 2.4
Name: STRling
Version: 2.5.9
Summary: Next-gen string pattern DSL & compiler
Author: TheCyberLocal
License: MIT
Project-URL: Homepage, https://github.com/TheCyberLocal/STRling
Project-URL: Documentation, https://github.com/TheCyberLocal/STRling/tree/main/docs
Project-URL: Issues, https://github.com/TheCyberLocal/STRling/issues
Keywords: strling,regex,regexp,regular expression,string,validation,pattern,parser,compiler,dsl,readable,beginner
Classifier: Programming Language :: Python :: 3
Classifier: License :: OSI Approved :: MIT License
Classifier: Development Status :: 4 - Beta
Classifier: Intended Audience :: Developers
Classifier: Topic :: Software Development :: Compilers
Classifier: Topic :: Software Development :: Libraries :: Python Modules
Classifier: Topic :: Text Processing
Requires-Python: >=3.8
